sunny/__init__.py
sunny/client.py
sunny/exceptions.py
sunny/types.py
sunny/resources/__init__.py
sunny/resources/bills.py
sunny/resources/bnpl.py
sunny/resources/crypto.py
sunny/resources/customers.py
sunny/resources/invoices.py
sunny/resources/mobile_money.py
sunny/resources/payments.py
sunny/resources/qr_codes.py
sunny/resources/refunds.py
sunny/resources/virtual_accounts.py
sunny/resources/webhooks.py
sunny_payments-1.0.0.dist-info/METADATA
sunny_payments-1.0.0.dist-info/WHEEL
sunny_payments-1.0.0.dist-info/top_level.txt
sunny_payments-1.0.0.dist-info/RECORD
