Metadata-Version: 2.4
Name: sunny-payments
Version: 1.0.0
Summary: Official Sunny Payments Python SDK - Payment processing made simple
Author: Sunny Payments Team
License: MIT
Project-URL: Homepage, https://sunnypayments.com
Project-URL: Documentation, https://docs.sunnypayments.com
Project-URL: Repository, https://github.com/SunnyPayments/sunny-python
Project-URL: Issues, https://github.com/SunnyPayments/sunny-python/issues
Keywords: sunny,payments,payment-gateway,mpesa,mobile-money,kenya,africa,fintech
Classifier: Development Status :: 5 - Production/Stable
Classifier: Intended Audience :: Developers
Classifier: License :: OSI Approved :: MIT License
Classifier: Operating System :: OS Independent
Classifier: Programming Language :: Python :: 3
Classifier: Programming Language :: Python :: 3.8
Classifier: Programming Language :: Python :: 3.9
Classifier: Programming Language :: Python :: 3.10
Classifier: Programming Language :: Python :: 3.11
Classifier: Programming Language :: Python :: 3.12
Classifier: Topic :: Software Development :: Libraries :: Python Modules
Classifier: Topic :: Office/Business :: Financial :: Point-Of-Sale
Requires-Python: >=3.8
Requires-Dist: requests>=2.28.0
Requires-Dist: typing-extensions>=4.0.0; python_version < "3.10"
Provides-Extra: dev
Requires-Dist: pytest>=7.0.0; extra == "dev"
Requires-Dist: pytest-asyncio>=0.20.0; extra == "dev"
Requires-Dist: responses>=0.22.0; extra == "dev"
Requires-Dist: black>=23.0.0; extra == "dev"
Requires-Dist: mypy>=1.0.0; extra == "dev"
Requires-Dist: types-requests>=2.28.0; extra == "dev"
